pytest_doctest_ellipsis_markers.py
pytest_doctest_ellipsis_markers-0.1.0.dist-info/DESCRIPTION.rst
pytest_doctest_ellipsis_markers-0.1.0.dist-info/METADATA
pytest_doctest_ellipsis_markers-0.1.0.dist-info/RECORD
pytest_doctest_ellipsis_markers-0.1.0.dist-info/WHEEL
pytest_doctest_ellipsis_markers-0.1.0.dist-info/entry_points.txt
pytest_doctest_ellipsis_markers-0.1.0.dist-info/metadata.json
pytest_doctest_ellipsis_markers-0.1.0.dist-info/top_level.txt
