Metadata-Version: 2.0
Name: pytest-doctest-ellipsis-markers
Version: 0.1.0
Summary: Setup additional values for ELLIPSIS_MARKER for doctests
Home-page: https://github.com/wooyek/pytest-doctest-ellipsis-markers
Author: Janusz Skonieczny
Author-email: js+pypi@bravelabs.pl
License: MIT
Platform: UNKNOWN
Classifier: Development Status :: 4 - Beta
Classifier: Framework :: Pytest
Classifier: Intended Audience :: Developers
Classifier: Topic :: Software Development :: Testing
Classifier: Programming Language :: Python
Classifier: Programming Language :: Python :: 2
Classifier: Programming Language :: Python :: 2.7
Classifier: Programming Language :: Python :: 3
Classifier: Programming Language :: Python :: 3.3
Classifier: Programming Language :: Python :: 3.4
Classifier: Programming Language :: Python :: 3.5
Classifier: Programming Language :: Python :: 3.6
Classifier: Programming Language :: Python :: Implementation :: CPython
Classifier: Programming Language :: Python :: Implementation :: PyPy
Classifier: Operating System :: OS Independent
Classifier: License :: OSI Approved :: MIT License
Requires-Dist: pytest (>=3.1.1)
